spstats/spstats.py
spstats-0.0.6.dist-info/LICENSE
spstats-0.0.6.dist-info/METADATA
spstats-0.0.6.dist-info/WHEEL
spstats-0.0.6.dist-info/top_level.txt
spstats-0.0.6.dist-info/RECORD
