Metadata-Version: 2.1
Name: spstats
Version: 0.0.6
Summary: useful tool , exist error
Home-page: https://github.com/VERUS2621/statis0001
Download-URL: https://github.com/VERUS2621/statis0001
Author: kangmin
Classifier: Programming Language :: Python :: 3
License-File: LICENSE
